mesa_types/__init__.py
mesa_types/document.py
mesa_types/py.typed
mesa_types/training_example.py
londonaicentre_mesa_types-2.0.0.dist-info/METADATA
londonaicentre_mesa_types-2.0.0.dist-info/WHEEL
londonaicentre_mesa_types-2.0.0.dist-info/top_level.txt
londonaicentre_mesa_types-2.0.0.dist-info/RECORD
