Metadata-Version: 2.4
Name: londonaicentre-mesa-types
Version: 2.0.0
Summary: MESA types
Author-email: "Dr. Joe Zhang" <jzhang@nhs.net>, Sophie Ratkai <s.ratkai@nhs.net>, Martin Chapman <contact@martinchapman.co.uk>
License-Expression: CC-BY-NC-ND-4.0
Requires-Python: >=3.12
Requires-Dist: pydantic>=2.12.5
